{
    "name": "6_mosaic_1",
    "imageCount": 6,
    "aspectRatio": 1.0,
    "frameDefinitions": [
        { "x": "0", "y": "0", "width": "0.5", "height": "0.333", "shape": { "type": "rectangle" } },
        { "x": "0", "y": "0.333", "width": "0.5", "height": "0.334", "shape": { "type": "rectangle" } },
        { "x": "0", "y": "0.667", "width": "0.5", "height": "0.333", "shape": { "type": "rectangle" } },
        { "x": "0.5", "y": "0", "width": "0.5", "height": "0.4", "shape": { "type": "rectangle" } },
        { "x": "0.5", "y": "0.4", "width": "0.5", "height": "0.3", "shape": { "type": "rectangle" } },
        { "x": "0.5", "y": "0.7", "width": "0.5", "height": "0.3", "shape": { "type": "rectangle" } }
    ]
} 