{
    "name": "overlap_2",
    "imageCount": 4,
    "aspectRatio": 1.0,
    "frameDefinitions": [
        {
            "x": "0.040",
            "y": "0.065",
            "width": "0.627",
            "height": "0.742",
            "rotation": "7.1",
            "shape": {
                "type": "circle"
            }
        },
        {
            "x": "0.389",
            "y": "0.106",
            "width": "0.458",
            "height": "0.538",
            "rotation": "-6.9",
            "shape": {
                "type": "circle"
            }
        },
        {
            "x": "0.128",
            "y": "0.161",
            "width": "0.645",
            "height": "0.640",
            "rotation": "-0.2",
            "shape": {
                "type": "circle"
            }
        },
        {
            "x": "0.129",
            "y": "0.179",
            "width": "0.500",
            "height": "0.576",
            "rotation": "-19.1",
            "shape": {
                "type": "circle"
            }
        }
    ]
}